pyulog/__init__.py
pyulog/_version.py
pyulog/core.py
pyulog/extract_gps_dump.py
pyulog/info.py
pyulog/messages.py
pyulog/params.py
pyulog/px4.py
pyulog/ulog2csv.py
pyulog/ulog2kml.py
test/__init__.py
test/test_ulog2csv.py
pyulog_Selab-1.0.6.dist-info/LICENSE.md
pyulog_Selab-1.0.6.dist-info/METADATA
pyulog_Selab-1.0.6.dist-info/WHEEL
pyulog_Selab-1.0.6.dist-info/entry_points.txt
pyulog_Selab-1.0.6.dist-info/top_level.txt
pyulog_Selab-1.0.6.dist-info/RECORD
