Metadata-Version: 2.1
Name: pyulog-Selab
Version: 1.0.6
Summary: Python log parser for ULog.
Home-page: https://github.com/takhashimoton/SEL-pyulog.git
Author: Beat Kueng
Author-email: beat-kueng@gmx.net
Maintainer: Takenori Hashimoto
Maintainer-email: takenori.hashimoto@selab.jp
License: BSD 3-Clause
Download-URL: https://github.com/takhashimoton/SEL-pyulog.git
Platform: Windows
Platform: Linux
Platform: Solaris
Platform: Mac OS-X
Platform: Unix
Classifier: Development Status :: 1 - Planning
Classifier: Intended Audience :: Science/Research
Classifier: Intended Audience :: Developers
Classifier: License :: OSI Approved :: BSD License
Classifier: Programming Language :: Python
Classifier: Programming Language :: Python :: 3
Classifier: Programming Language :: Other
Classifier: Topic :: Software Development
Classifier: Topic :: Scientific/Engineering :: Artificial Intelligence
Classifier: Topic :: Scientific/Engineering :: Mathematics
Classifier: Topic :: Scientific/Engineering :: Physics
Classifier: Operating System :: Microsoft :: Windows
Classifier: Operating System :: POSIX
Classifier: Operating System :: Unix
Classifier: Operating System :: MacOS
Requires-Dist: numpy
